pydeequ/__init__.py
pydeequ/analyzers.py
pydeequ/anomaly_detection.py
pydeequ/check_functions.py
pydeequ/checks.py
pydeequ/configs.py
pydeequ/metrics.py
pydeequ/pandas_utils.py
pydeequ/profiles.py
pydeequ/repository.py
pydeequ/scala_utils.py
pydeequ/suggestions.py
pydeequ/verification.py
pydeequ-1.3.0.dist-info/LICENSE
pydeequ-1.3.0.dist-info/METADATA
pydeequ-1.3.0.dist-info/WHEEL
pydeequ-1.3.0.dist-info/RECORD
