Metadata-Version: 2.1
Name: pydeequ
Version: 1.3.0
Summary: PyDeequ - Unit Tests for Data
Home-page: https://pydeequ.readthedocs.io
License: Apache-2.0
Keywords: deequ,pydeequ,data-engineering,data-quality,data-profiling,dataquality,dataunittest,data-unit-tests,data-profilers
Author: Chenyang Liu
Author-email: peterl@amazon.com
Maintainer: Chenyang Liu
Maintainer-email: peterl@amazon.com
Requires-Python: >=3.7,<4
Classifier: Development Status :: 4 - Beta
Classifier: License :: OSI Approved :: Apache Software License
Classifier: Programming Language :: Python :: 3
Classifier: Programming Language :: Python :: 3.7
Classifier: Programming Language :: Python :: 3.8
Classifier: Programming Language :: Python :: 3.9
Classifier: Programming Language :: Python :: 3.10
Classifier: Programming Language :: Python :: 3.11
Classifier: Programming Language :: Python :: 3.12
Provides-Extra: pyspark
Requires-Dist: numpy (>=1.14.1)
Requires-Dist: pandas (>=0.23.0)
Requires-Dist: pyspark (>=2.4.7,<3.3.0) ; extra == "pyspark"
Project-URL: Documentation, https://pydeequ.readthedocs.io
Project-URL: Repository, https://github.com/awslabs/python-deequ
